{
"type": "FeatureCollection",
"name": "randomPnt",
"crs": { "type": "name", "properties": { "name": "urn:ogc:def:crs:OGC:1.3:CRS84" } },
"features": [
{ "type": "Feature", "properties": { "id": 0 }, "geometry": { "type": "Point", "coordinates": [ 119.872903925733596, 30.308330274859365 ] } },
{ "type": "Feature", "properties": { "id": 1 }, "geometry": { "type": "Point", "coordinates": [ 119.952601582677147, 30.253498274127921 ] } },
{ "type": "Feature", "properties": { "id": 2 }, "geometry": { "type": "Point", "coordinates": [ 119.751004681242847, 30.222515623948929 ] } },
{ "type": "Feature", "properties": { "id": 3 }, "geometry": { "type": "Point", "coordinates": [ 119.881607509896924, 30.287196962298868 ] } },
{ "type": "Feature", "properties": { "id": 4 }, "geometry": { "type": "Point", "coordinates": [ 119.921761415542079, 30.272053248526976 ] } },
{ "type": "Feature", "properties": { "id": 5 }, "geometry": { "type": "Point", "coordinates": [ 120.066781766032577, 30.283102065363689 ] } },
{ "type": "Feature", "properties": { "id": 6 }, "geometry": { "type": "Point", "coordinates": [ 120.081394876837408, 30.307317375682096 ] } },
{ "type": "Feature", "properties": { "id": 7 }, "geometry": { "type": "Point", "coordinates": [ 119.905916737074577, 30.268342952729338 ] } },
{ "type": "Feature", "properties": { "id": 8 }, "geometry": { "type": "Point", "coordinates": [ 119.893925158924588, 30.327117660110062 ] } },
{ "type": "Feature", "properties": { "id": 9 }, "geometry": { "type": "Point", "coordinates": [ 120.020015019726131, 30.301902143694484 ] } },
{ "type": "Feature", "properties": { "id": 10 }, "geometry": { "type": "Point", "coordinates": [ 119.895839084598535, 30.311121193182135 ] } },
{ "type": "Feature", "properties": { "id": 11 }, "geometry": { "type": "Point", "coordinates": [ 119.970048934488574, 30.34027107639054 ] } },
{ "type": "Feature", "properties": { "id": 12 }, "geometry": { "type": "Point", "coordinates": [ 120.00727713654382, 30.32551033881958 ] } },
{ "type": "Feature", "properties": { "id": 13 }, "geometry": { "type": "Point", "coordinates": [ 119.98764349023503, 30.304047812837517 ] } },
{ "type": "Feature", "properties": { "id": 14 }, "geometry": { "type": "Point", "coordinates": [ 119.824747959256754, 30.295179429496205 ] } },
{ "type": "Feature", "properties": { "id": 15 }, "geometry": { "type": "Point", "coordinates": [ 119.783367767381719, 30.305372427537986 ] } },
{ "type": "Feature", "properties": { "id": 16 }, "geometry": { "type": "Point", "coordinates": [ 119.726221579709971, 30.277978228138245 ] } },
{ "type": "Feature", "properties": { "id": 17 }, "geometry": { "type": "Point", "coordinates": [ 120.028618250401564, 30.265719108043854 ] } },
{ "type": "Feature", "properties": { "id": 18 }, "geometry": { "type": "Point", "coordinates": [ 119.960040484638768, 30.299130121461907 ] } },
{ "type": "Feature", "properties": { "id": 19 }, "geometry": { "type": "Point", "coordinates": [ 119.900266475736586, 30.330824431180709 ] } },
{ "type": "Feature", "properties": { "id": 20 }, "geometry": { "type": "Point", "coordinates": [ 119.788278047231316, 30.252039674634112 ] } },
{ "type": "Feature", "properties": { "id": 21 }, "geometry": { "type": "Point", "coordinates": [ 119.72282400362829, 30.250869653343663 ] } },
{ "type": "Feature", "properties": { "id": 22 }, "geometry": { "type": "Point", "coordinates": [ 119.765434695311086, 30.257740436477309 ] } },
{ "type": "Feature", "properties": { "id": 23 }, "geometry": { "type": "Point", "coordinates": [ 119.901866078793958, 30.276006002074435 ] } },
{ "type": "Feature", "properties": { "id": 24 }, "geometry": { "type": "Point", "coordinates": [ 119.77913733747738, 30.316782130831438 ] } },
{ "type": "Feature", "properties": { "id": 25 }, "geometry": { "type": "Point", "coordinates": [ 120.013624212445009, 30.294283838512545 ] } },
{ "type": "Feature", "properties": { "id": 26 }, "geometry": { "type": "Point", "coordinates": [ 119.975008853720439, 30.268468263794844 ] } },
{ "type": "Feature", "properties": { "id": 27 }, "geometry": { "type": "Point", "coordinates": [ 119.824600888058242, 30.271837718754753 ] } },
{ "type": "Feature", "properties": { "id": 28 }, "geometry": { "type": "Point", "coordinates": [ 119.972322352033331, 30.238980050912819 ] } },
{ "type": "Feature", "properties": { "id": 29 }, "geometry": { "type": "Point", "coordinates": [ 120.08598138524296, 30.303352963753365 ] } },
{ "type": "Feature", "properties": { "id": 30 }, "geometry": { "type": "Point", "coordinates": [ 119.902871086739538, 30.30245053000214 ] } },
{ "type": "Feature", "properties": { "id": 31 }, "geometry": { "type": "Point", "coordinates": [ 120.044420980512029, 30.299501796692745 ] } },
{ "type": "Feature", "properties": { "id": 32 }, "geometry": { "type": "Point", "coordinates": [ 119.773528026687529, 30.338014480714328 ] } },
{ "type": "Feature", "properties": { "id": 33 }, "geometry": { "type": "Point", "coordinates": [ 119.774629413501799, 30.269666604964591 ] } },
{ "type": "Feature", "properties": { "id": 34 }, "geometry": { "type": "Point", "coordinates": [ 119.764702711430374, 30.238086967235841 ] } },
{ "type": "Feature", "properties": { "id": 35 }, "geometry": { "type": "Point", "coordinates": [ 119.794507353927102, 30.315346909278563 ] } },
{ "type": "Feature", "properties": { "id": 36 }, "geometry": { "type": "Point", "coordinates": [ 119.917785404465704, 30.328025825044918 ] } },
{ "type": "Feature", "properties": { "id": 37 }, "geometry": { "type": "Point", "coordinates": [ 119.905975345981815, 30.244813004655903 ] } },
{ "type": "Feature", "properties": { "id": 38 }, "geometry": { "type": "Point", "coordinates": [ 119.716042978132577, 30.218065730992759 ] } },
{ "type": "Feature", "properties": { "id": 39 }, "geometry": { "type": "Point", "coordinates": [ 120.034685117766742, 30.329976051368256 ] } },
{ "type": "Feature", "properties": { "id": 40 }, "geometry": { "type": "Point", "coordinates": [ 119.899788673971457, 30.263364506447211 ] } },
{ "type": "Feature", "properties": { "id": 41 }, "geometry": { "type": "Point", "coordinates": [ 119.957839777754259, 30.275585669425027 ] } },
{ "type": "Feature", "properties": { "id": 42 }, "geometry": { "type": "Point", "coordinates": [ 119.8253575789834, 30.25806822940655 ] } },
{ "type": "Feature", "properties": { "id": 43 }, "geometry": { "type": "Point", "coordinates": [ 119.700376352932892, 30.211993590684262 ] } },
{ "type": "Feature", "properties": { "id": 44 }, "geometry": { "type": "Point", "coordinates": [ 119.741858161654008, 30.276738566148197 ] } },
{ "type": "Feature", "properties": { "id": 45 }, "geometry": { "type": "Point", "coordinates": [ 119.928872922538133, 30.317233292908782 ] } },
{ "type": "Feature", "properties": { "id": 46 }, "geometry": { "type": "Point", "coordinates": [ 119.766816502688087, 30.213431041994475 ] } },
{ "type": "Feature", "properties": { "id": 47 }, "geometry": { "type": "Point", "coordinates": [ 119.778706767164721, 30.2113169976544 ] } },
{ "type": "Feature", "properties": { "id": 48 }, "geometry": { "type": "Point", "coordinates": [ 120.055002184109739, 30.300599524822506 ] } },
{ "type": "Feature", "properties": { "id": 49 }, "geometry": { "type": "Point", "coordinates": [ 119.903162661331379, 30.323692516710487 ] } },
{ "type": "Feature", "properties": { "id": 50 }, "geometry": { "type": "Point", "coordinates": [ 119.993748382154365, 30.217924718455969 ] } },
{ "type": "Feature", "properties": { "id": 51 }, "geometry": { "type": "Point", "coordinates": [ 119.711703885093087, 30.205973499689698 ] } },
{ "type": "Feature", "properties": { "id": 52 }, "geometry": { "type": "Point", "coordinates": [ 120.012358660366544, 30.224964909517436 ] } },
{ "type": "Feature", "properties": { "id": 53 }, "geometry": { "type": "Point", "coordinates": [ 119.819472457504261, 30.236688860390156 ] } },
{ "type": "Feature", "properties": { "id": 54 }, "geometry": { "type": "Point", "coordinates": [ 119.816350687161588, 30.296250688704113 ] } },
{ "type": "Feature", "properties": { "id": 55 }, "geometry": { "type": "Point", "coordinates": [ 119.895198371439761, 30.282670932851303 ] } },
{ "type": "Feature", "properties": { "id": 56 }, "geometry": { "type": "Point", "coordinates": [ 119.967362524227809, 30.305284596143256 ] } },
{ "type": "Feature", "properties": { "id": 57 }, "geometry": { "type": "Point", "coordinates": [ 120.024791923580281, 30.34237199581451 ] } },
{ "type": "Feature", "properties": { "id": 58 }, "geometry": { "type": "Point", "coordinates": [ 119.98951224345609, 30.326789569627081 ] } },
{ "type": "Feature", "properties": { "id": 59 }, "geometry": { "type": "Point", "coordinates": [ 119.99306615898584, 30.259142366266609 ] } },
{ "type": "Feature", "properties": { "id": 60 }, "geometry": { "type": "Point", "coordinates": [ 120.016108914405976, 30.235243108487683 ] } },
{ "type": "Feature", "properties": { "id": 61 }, "geometry": { "type": "Point", "coordinates": [ 119.876982921648121, 30.25933698428171 ] } },
{ "type": "Feature", "properties": { "id": 62 }, "geometry": { "type": "Point", "coordinates": [ 119.729294637690046, 30.226032949568765 ] } },
{ "type": "Feature", "properties": { "id": 63 }, "geometry": { "type": "Point", "coordinates": [ 119.735968141200189, 30.273257954118034 ] } },
{ "type": "Feature", "properties": { "id": 64 }, "geometry": { "type": "Point", "coordinates": [ 119.835300574630111, 30.288962877962927 ] } },
{ "type": "Feature", "properties": { "id": 65 }, "geometry": { "type": "Point", "coordinates": [ 119.804157920569509, 30.251146764119948 ] } },
{ "type": "Feature", "properties": { "id": 66 }, "geometry": { "type": "Point", "coordinates": [ 120.024724551211435, 30.218993252711527 ] } },
{ "type": "Feature", "properties": { "id": 67 }, "geometry": { "type": "Point", "coordinates": [ 120.040041221849876, 30.293947728894974 ] } },
{ "type": "Feature", "properties": { "id": 68 }, "geometry": { "type": "Point", "coordinates": [ 119.737831259466304, 30.254471980102565 ] } },
{ "type": "Feature", "properties": { "id": 69 }, "geometry": { "type": "Point", "coordinates": [ 119.801014048446987, 30.260481203507283 ] } },
{ "type": "Feature", "properties": { "id": 70 }, "geometry": { "type": "Point", "coordinates": [ 119.72700007424767, 30.208892130913934 ] } },
{ "type": "Feature", "properties": { "id": 71 }, "geometry": { "type": "Point", "coordinates": [ 119.776777970720445, 30.296154226963882 ] } },
{ "type": "Feature", "properties": { "id": 72 }, "geometry": { "type": "Point", "coordinates": [ 119.934888083340724, 30.330445530954655 ] } },
{ "type": "Feature", "properties": { "id": 73 }, "geometry": { "type": "Point", "coordinates": [ 119.849196526563802, 30.250145935405275 ] } },
{ "type": "Feature", "properties": { "id": 74 }, "geometry": { "type": "Point", "coordinates": [ 119.968186941869433, 30.329175090131002 ] } },
{ "type": "Feature", "properties": { "id": 75 }, "geometry": { "type": "Point", "coordinates": [ 119.866250415913939, 30.285037553943571 ] } },
{ "type": "Feature", "properties": { "id": 76 }, "geometry": { "type": "Point", "coordinates": [ 119.990194467284198, 30.290306085445295 ] } },
{ "type": "Feature", "properties": { "id": 77 }, "geometry": { "type": "Point", "coordinates": [ 119.806186778373643, 30.293591496080978 ] } },
{ "type": "Feature", "properties": { "id": 78 }, "geometry": { "type": "Point", "coordinates": [ 119.73745314682246, 30.218680484627537 ] } },
{ "type": "Feature", "properties": { "id": 79 }, "geometry": { "type": "Point", "coordinates": [ 120.007274888317639, 30.265831851816397 ] } },
{ "type": "Feature", "properties": { "id": 80 }, "geometry": { "type": "Point", "coordinates": [ 119.903487122468377, 30.282644907749646 ] } },
{ "type": "Feature", "properties": { "id": 81 }, "geometry": { "type": "Point", "coordinates": [ 120.010850107437903, 30.237419038459045 ] } },
{ "type": "Feature", "properties": { "id": 82 }, "geometry": { "type": "Point", "coordinates": [ 120.07598968317393, 30.312390974126803 ] } },
{ "type": "Feature", "properties": { "id": 83 }, "geometry": { "type": "Point", "coordinates": [ 119.987868110398296, 30.331910642257608 ] } },
{ "type": "Feature", "properties": { "id": 84 }, "geometry": { "type": "Point", "coordinates": [ 119.998370523455435, 30.262559680441939 ] } },
{ "type": "Feature", "properties": { "id": 85 }, "geometry": { "type": "Point", "coordinates": [ 119.728836770503534, 30.264431090522969 ] } },
{ "type": "Feature", "properties": { "id": 86 }, "geometry": { "type": "Point", "coordinates": [ 119.936463149220629, 30.296394897889652 ] } },
{ "type": "Feature", "properties": { "id": 87 }, "geometry": { "type": "Point", "coordinates": [ 120.013427270493011, 30.277654874043861 ] } },
{ "type": "Feature", "properties": { "id": 88 }, "geometry": { "type": "Point", "coordinates": [ 120.028992482487979, 30.297237002837225 ] } },
{ "type": "Feature", "properties": { "id": 89 }, "geometry": { "type": "Point", "coordinates": [ 119.927739568345856, 30.326303511135798 ] } },
{ "type": "Feature", "properties": { "id": 90 }, "geometry": { "type": "Point", "coordinates": [ 120.043303838185295, 30.22316614722671 ] } },
{ "type": "Feature", "properties": { "id": 91 }, "geometry": { "type": "Point", "coordinates": [ 119.843194048689099, 30.306786405215966 ] } },
{ "type": "Feature", "properties": { "id": 92 }, "geometry": { "type": "Point", "coordinates": [ 119.78217619334491, 30.267748639821352 ] } },
{ "type": "Feature", "properties": { "id": 93 }, "geometry": { "type": "Point", "coordinates": [ 119.925050407941583, 30.291331007700141 ] } },
{ "type": "Feature", "properties": { "id": 94 }, "geometry": { "type": "Point", "coordinates": [ 119.769155385591773, 30.253858512514824 ] } },
{ "type": "Feature", "properties": { "id": 95 }, "geometry": { "type": "Point", "coordinates": [ 120.04556706853954, 30.348917638139522 ] } },
{ "type": "Feature", "properties": { "id": 96 }, "geometry": { "type": "Point", "coordinates": [ 119.729808716803078, 30.251043157640865 ] } },
{ "type": "Feature", "properties": { "id": 97 }, "geometry": { "type": "Point", "coordinates": [ 119.895897815292798, 30.255592640576392 ] } },
{ "type": "Feature", "properties": { "id": 98 }, "geometry": { "type": "Point", "coordinates": [ 119.748083758033502, 30.242594159443509 ] } },
{ "type": "Feature", "properties": { "id": 99 }, "geometry": { "type": "Point", "coordinates": [ 119.769743683826434, 30.272128872163456 ] } },
{ "type": "Feature", "properties": { "id": 100 }, "geometry": { "type": "Point", "coordinates": [ 119.854922463248201, 30.265122770966236 ] } },
{ "type": "Feature", "properties": { "id": 101 }, "geometry": { "type": "Point", "coordinates": [ 120.034603812832842, 30.228270676406435 ] } },
{ "type": "Feature", "properties": { "id": 102 }, "geometry": { "type": "Point", "coordinates": [ 120.052527381178336, 30.311222445284809 ] } },
{ "type": "Feature", "properties": { "id": 103 }, "geometry": { "type": "Point", "coordinates": [ 119.753427854601185, 30.280710194959429 ] } },
{ "type": "Feature", "properties": { "id": 104 }, "geometry": { "type": "Point", "coordinates": [ 119.937767319297734, 30.325446968493793 ] } },
{ "type": "Feature", "properties": { "id": 105 }, "geometry": { "type": "Point", "coordinates": [ 119.91110780288578, 30.301423704187425 ] } },
{ "type": "Feature", "properties": { "id": 106 }, "geometry": { "type": "Point", "coordinates": [ 120.045293734819197, 30.305373548741194 ] } },
{ "type": "Feature", "properties": { "id": 107 }, "geometry": { "type": "Point", "coordinates": [ 120.044507415237192, 30.236318773326587 ] } },
{ "type": "Feature", "properties": { "id": 108 }, "geometry": { "type": "Point", "coordinates": [ 120.000477162003534, 30.246931871015555 ] } },
{ "type": "Feature", "properties": { "id": 109 }, "geometry": { "type": "Point", "coordinates": [ 120.043570226597808, 30.2818057112448 ] } },
{ "type": "Feature", "properties": { "id": 110 }, "geometry": { "type": "Point", "coordinates": [ 120.050233765880222, 30.345914618040123 ] } },
{ "type": "Feature", "properties": { "id": 111 }, "geometry": { "type": "Point", "coordinates": [ 119.855814986918944, 30.272392108908328 ] } },
{ "type": "Feature", "properties": { "id": 112 }, "geometry": { "type": "Point", "coordinates": [ 119.786920679827006, 30.235206544951293 ] } },
{ "type": "Feature", "properties": { "id": 113 }, "geometry": { "type": "Point", "coordinates": [ 119.720104072051569, 30.260382581218551 ] } },
{ "type": "Feature", "properties": { "id": 114 }, "geometry": { "type": "Point", "coordinates": [ 119.93865622215985, 30.319484492964307 ] } },
{ "type": "Feature", "properties": { "id": 115 }, "geometry": { "type": "Point", "coordinates": [ 119.74426811995086, 30.261581320583836 ] } },
{ "type": "Feature", "properties": { "id": 116 }, "geometry": { "type": "Point", "coordinates": [ 119.860743575094901, 30.279991160234331 ] } },
{ "type": "Feature", "properties": { "id": 117 }, "geometry": { "type": "Point", "coordinates": [ 119.965899197108413, 30.299481592610078 ] } },
{ "type": "Feature", "properties": { "id": 118 }, "geometry": { "type": "Point", "coordinates": [ 119.993379239193942, 30.296617640735779 ] } },
{ "type": "Feature", "properties": { "id": 119 }, "geometry": { "type": "Point", "coordinates": [ 120.053147411498301, 30.351646083151337 ] } },
{ "type": "Feature", "properties": { "id": 120 }, "geometry": { "type": "Point", "coordinates": [ 119.983437770110513, 30.277887986714013 ] } },
{ "type": "Feature", "properties": { "id": 121 }, "geometry": { "type": "Point", "coordinates": [ 120.002146863638899, 30.206964974930919 ] } },
{ "type": "Feature", "properties": { "id": 122 }, "geometry": { "type": "Point", "coordinates": [ 119.9156807415266, 30.343033812589507 ] } },
{ "type": "Feature", "properties": { "id": 123 }, "geometry": { "type": "Point", "coordinates": [ 119.928725289599043, 30.286306487729931 ] } },
{ "type": "Feature", "properties": { "id": 124 }, "geometry": { "type": "Point", "coordinates": [ 119.808140838417216, 30.255849431668558 ] } },
{ "type": "Feature", "properties": { "id": 125 }, "geometry": { "type": "Point", "coordinates": [ 119.773291701006997, 30.206111818522164 ] } },
{ "type": "Feature", "properties": { "id": 126 }, "geometry": { "type": "Point", "coordinates": [ 119.906675531052002, 30.288202873129183 ] } },
{ "type": "Feature", "properties": { "id": 127 }, "geometry": { "type": "Point", "coordinates": [ 120.042110230578572, 30.325109134532774 ] } },
{ "type": "Feature", "properties": { "id": 128 }, "geometry": { "type": "Point", "coordinates": [ 119.74358940971311, 30.269139692118969 ] } },
{ "type": "Feature", "properties": { "id": 129 }, "geometry": { "type": "Point", "coordinates": [ 119.745436767985623, 30.256206042038041 ] } },
{ "type": "Feature", "properties": { "id": 130 }, "geometry": { "type": "Point", "coordinates": [ 120.055824469618358, 30.292074365849746 ] } },
{ "type": "Feature", "properties": { "id": 131 }, "geometry": { "type": "Point", "coordinates": [ 119.741053888334164, 30.242166236146527 ] } },
{ "type": "Feature", "properties": { "id": 132 }, "geometry": { "type": "Point", "coordinates": [ 120.029464793569929, 30.31151252687696 ] } },
{ "type": "Feature", "properties": { "id": 133 }, "geometry": { "type": "Point", "coordinates": [ 119.931196004007703, 30.270709780950323 ] } },
{ "type": "Feature", "properties": { "id": 134 }, "geometry": { "type": "Point", "coordinates": [ 119.927281692531054, 30.263454804089172 ] } },
{ "type": "Feature", "properties": { "id": 135 }, "geometry": { "type": "Point", "coordinates": [ 119.776203382290859, 30.262888421609084 ] } },
{ "type": "Feature", "properties": { "id": 136 }, "geometry": { "type": "Point", "coordinates": [ 119.873386675039598, 30.31478311068566 ] } },
{ "type": "Feature", "properties": { "id": 137 }, "geometry": { "type": "Point", "coordinates": [ 119.840618892407079, 30.265762624801006 ] } },
{ "type": "Feature", "properties": { "id": 138 }, "geometry": { "type": "Point", "coordinates": [ 120.036027432646378, 30.324409789060905 ] } },
{ "type": "Feature", "properties": { "id": 139 }, "geometry": { "type": "Point", "coordinates": [ 119.998573827264195, 30.340081932933145 ] } },
{ "type": "Feature", "properties": { "id": 140 }, "geometry": { "type": "Point", "coordinates": [ 119.99525337462147, 30.306094818399608 ] } },
{ "type": "Feature", "properties": { "id": 141 }, "geometry": { "type": "Point", "coordinates": [ 120.048918960757334, 30.238838631162892 ] } },
{ "type": "Feature", "properties": { "id": 142 }, "geometry": { "type": "Point", "coordinates": [ 119.958221914912357, 30.324680582679289 ] } },
{ "type": "Feature", "properties": { "id": 143 }, "geometry": { "type": "Point", "coordinates": [ 119.820243509380362, 30.275125694223956 ] } },
{ "type": "Feature", "properties": { "id": 144 }, "geometry": { "type": "Point", "coordinates": [ 120.042892729405139, 30.288243002748494 ] } },
{ "type": "Feature", "properties": { "id": 145 }, "geometry": { "type": "Point", "coordinates": [ 119.953198018174177, 30.308550453385543 ] } },
{ "type": "Feature", "properties": { "id": 146 }, "geometry": { "type": "Point", "coordinates": [ 119.983426023370058, 30.239130993835921 ] } },
{ "type": "Feature", "properties": { "id": 147 }, "geometry": { "type": "Point", "coordinates": [ 120.041001718092275, 30.247746434468986 ] } },
{ "type": "Feature", "properties": { "id": 148 }, "geometry": { "type": "Point", "coordinates": [ 120.063150964914215, 30.275715684469574 ] } },
{ "type": "Feature", "properties": { "id": 149 }, "geometry": { "type": "Point", "coordinates": [ 119.984198892278272, 30.270091028065888 ] } },
{ "type": "Feature", "properties": { "id": 150 }, "geometry": { "type": "Point", "coordinates": [ 119.944047134200787, 30.345963928005705 ] } },
{ "type": "Feature", "properties": { "id": 151 }, "geometry": { "type": "Point", "coordinates": [ 120.070977229716092, 30.268100866836733 ] } },
{ "type": "Feature", "properties": { "id": 152 }, "geometry": { "type": "Point", "coordinates": [ 120.008022105193035, 30.214852270623222 ] } },
{ "type": "Feature", "properties": { "id": 153 }, "geometry": { "type": "Point", "coordinates": [ 120.005286087974781, 30.312983082505546 ] } },
{ "type": "Feature", "properties": { "id": 154 }, "geometry": { "type": "Point", "coordinates": [ 119.767040068758988, 30.340342488392263 ] } },
{ "type": "Feature", "properties": { "id": 155 }, "geometry": { "type": "Point", "coordinates": [ 119.97672771489475, 30.248232094359125 ] } },
{ "type": "Feature", "properties": { "id": 156 }, "geometry": { "type": "Point", "coordinates": [ 119.973184186248304, 30.258614363911466 ] } },
{ "type": "Feature", "properties": { "id": 157 }, "geometry": { "type": "Point", "coordinates": [ 119.771528553814377, 30.216554256490813 ] } },
{ "type": "Feature", "properties": { "id": 158 }, "geometry": { "type": "Point", "coordinates": [ 119.855327678389685, 30.302013668189371 ] } },
{ "type": "Feature", "properties": { "id": 159 }, "geometry": { "type": "Point", "coordinates": [ 120.036882075728698, 30.313155153284828 ] } },
{ "type": "Feature", "properties": { "id": 160 }, "geometry": { "type": "Point", "coordinates": [ 120.072658394631318, 30.273234064152152 ] } },
{ "type": "Feature", "properties": { "id": 161 }, "geometry": { "type": "Point", "coordinates": [ 119.909160702727419, 30.294622959568766 ] } },
{ "type": "Feature", "properties": { "id": 162 }, "geometry": { "type": "Point", "coordinates": [ 119.891208066685465, 30.251023723859486 ] } },
{ "type": "Feature", "properties": { "id": 163 }, "geometry": { "type": "Point", "coordinates": [ 119.795801676570647, 30.251886723576252 ] } },
{ "type": "Feature", "properties": { "id": 164 }, "geometry": { "type": "Point", "coordinates": [ 119.792718178624227, 30.273377919749048 ] } },
{ "type": "Feature", "properties": { "id": 165 }, "geometry": { "type": "Point", "coordinates": [ 120.018833062411204, 30.289396718732185 ] } },
{ "type": "Feature", "properties": { "id": 166 }, "geometry": { "type": "Point", "coordinates": [ 119.779397450708828, 30.331539619133729 ] } },
{ "type": "Feature", "properties": { "id": 167 }, "geometry": { "type": "Point", "coordinates": [ 119.998223520275019, 30.2846205376113 ] } },
{ "type": "Feature", "properties": { "id": 168 }, "geometry": { "type": "Point", "coordinates": [ 119.771903772892756, 30.293401194265027 ] } },
{ "type": "Feature", "properties": { "id": 169 }, "geometry": { "type": "Point", "coordinates": [ 119.788145814046572, 30.323392916488153 ] } },
{ "type": "Feature", "properties": { "id": 170 }, "geometry": { "type": "Point", "coordinates": [ 119.817071827799595, 30.261024262491208 ] } },
{ "type": "Feature", "properties": { "id": 171 }, "geometry": { "type": "Point", "coordinates": [ 119.74461392275353, 30.219607068125953 ] } },
{ "type": "Feature", "properties": { "id": 172 }, "geometry": { "type": "Point", "coordinates": [ 119.870671026412154, 30.271935241295552 ] } },
{ "type": "Feature", "properties": { "id": 173 }, "geometry": { "type": "Point", "coordinates": [ 120.030474199946198, 30.252709195343854 ] } },
{ "type": "Feature", "properties": { "id": 174 }, "geometry": { "type": "Point", "coordinates": [ 119.82511506830167, 30.284359319516415 ] } },
{ "type": "Feature", "properties": { "id": 175 }, "geometry": { "type": "Point", "coordinates": [ 119.879738792296394, 30.298071219031957 ] } },
{ "type": "Feature", "properties": { "id": 176 }, "geometry": { "type": "Point", "coordinates": [ 119.956195735243924, 30.314732769571549 ] } },
{ "type": "Feature", "properties": { "id": 177 }, "geometry": { "type": "Point", "coordinates": [ 119.861222749002096, 30.286269386652027 ] } },
{ "type": "Feature", "properties": { "id": 178 }, "geometry": { "type": "Point", "coordinates": [ 119.869288300518278, 30.303255018824824 ] } },
{ "type": "Feature", "properties": { "id": 179 }, "geometry": { "type": "Point", "coordinates": [ 119.98082287141257, 30.290985641243662 ] } },
{ "type": "Feature", "properties": { "id": 180 }, "geometry": { "type": "Point", "coordinates": [ 119.809364523159317, 30.278044103017272 ] } },
{ "type": "Feature", "properties": { "id": 181 }, "geometry": { "type": "Point", "coordinates": [ 119.965074869724532, 30.314165143139526 ] } },
{ "type": "Feature", "properties": { "id": 182 }, "geometry": { "type": "Point", "coordinates": [ 119.958738323524244, 30.336213903012236 ] } },
{ "type": "Feature", "properties": { "id": 183 }, "geometry": { "type": "Point", "coordinates": [ 119.855188771751727, 30.291909416744737 ] } },
{ "type": "Feature", "properties": { "id": 184 }, "geometry": { "type": "Point", "coordinates": [ 120.019662459271515, 30.275693511036462 ] } },
{ "type": "Feature", "properties": { "id": 185 }, "geometry": { "type": "Point", "coordinates": [ 120.055952259641245, 30.31898075157266 ] } },
{ "type": "Feature", "properties": { "id": 186 }, "geometry": { "type": "Point", "coordinates": [ 119.75189325518464, 30.265436698094653 ] } },
{ "type": "Feature", "properties": { "id": 187 }, "geometry": { "type": "Point", "coordinates": [ 119.969943199411944, 30.250466232412705 ] } },
{ "type": "Feature", "properties": { "id": 188 }, "geometry": { "type": "Point", "coordinates": [ 120.011969499163598, 30.230189671465737 ] } },
{ "type": "Feature", "properties": { "id": 189 }, "geometry": { "type": "Point", "coordinates": [ 120.03366232345185, 30.304151258082516 ] } },
{ "type": "Feature", "properties": { "id": 190 }, "geometry": { "type": "Point", "coordinates": [ 119.743483492213301, 30.224800898562513 ] } },
{ "type": "Feature", "properties": { "id": 191 }, "geometry": { "type": "Point", "coordinates": [ 119.77949361049015, 30.217959521053192 ] } },
{ "type": "Feature", "properties": { "id": 192 }, "geometry": { "type": "Point", "coordinates": [ 120.019151260739903, 30.217551619183304 ] } },
{ "type": "Feature", "properties": { "id": 193 }, "geometry": { "type": "Point", "coordinates": [ 119.907478462900428, 30.329202741499437 ] } },
{ "type": "Feature", "properties": { "id": 194 }, "geometry": { "type": "Point", "coordinates": [ 119.946607963976717, 30.316728621015638 ] } },
{ "type": "Feature", "properties": { "id": 195 }, "geometry": { "type": "Point", "coordinates": [ 120.081592394696813, 30.318701182428651 ] } },
{ "type": "Feature", "properties": { "id": 196 }, "geometry": { "type": "Point", "coordinates": [ 119.814573235698603, 30.234194884972261 ] } },
{ "type": "Feature", "properties": { "id": 197 }, "geometry": { "type": "Point", "coordinates": [ 119.840239849180378, 30.252438885781292 ] } },
{ "type": "Feature", "properties": { "id": 198 }, "geometry": { "type": "Point", "coordinates": [ 119.799516218256727, 30.320579434574594 ] } },
{ "type": "Feature", "properties": { "id": 199 }, "geometry": { "type": "Point", "coordinates": [ 119.722046343618175, 30.271392839823037 ] } }
]
}
